fff_mock_gen/fff_mock_gen.py
fff_mock_gen-0.1.3.dist-info/LICENSE
fff_mock_gen-0.1.3.dist-info/METADATA
fff_mock_gen-0.1.3.dist-info/WHEEL
fff_mock_gen-0.1.3.dist-info/entry_points.txt
fff_mock_gen-0.1.3.dist-info/top_level.txt
fff_mock_gen-0.1.3.dist-info/RECORD
