Metadata-Version: 2.1
Name: fff-mock-gen
Version: 0.1.3
Summary: Automatic mock generation using FFF
Home-page: https://github.com/Amcolex/fff-mock-gen.git
Author: Alex Pabouctsidis
Author-email: alex.pabouct@gmail.com
License-File: LICENSE
